human_date_parser/__init__.py
human_date_parser/parser.py
human_date_parser-0.1.2.dist-info/METADATA
human_date_parser-0.1.2.dist-info/WHEEL
human_date_parser-0.1.2.dist-info/top_level.txt
human_date_parser-0.1.2.dist-info/RECORD
